AUTHORS.txt
LICENSE.txt
MANIFEST.in
README.rst
setup.py
django_adaptive/__init__.py
django_adaptive/app_directories.py
django_adaptive/cached.py
django_adaptive/filesystem.py
django_adaptive/loader_utils.py
django_adaptive/middleware.py
django_adaptive.egg-info/PKG-INFO
django_adaptive.egg-info/SOURCES.txt
django_adaptive.egg-info/dependency_links.txt
django_adaptive.egg-info/pbr.json
django_adaptive.egg-info/requires.txt
django_adaptive.egg-info/top_level.txt