Metadata-Version: 1.1
Name: django-adaptive
Version: 1.0.2
Summary: Manages to load templates according to the type of device to        a specific directory prefix.
Home-page: http://www.revsquare.com
Author: Guillaume Pousseo <guillaumepousseo@revsquare.com>,        Tomasz Roszko <tomaszroszko@revsquare.com>,        Rafal Selewonko <rafalselewonko@revsquare.com>
Author-email: UNKNOWN
License: BSD License
Platform: OS Independent
Classifier: Development Status :: 5 - Production/Stable
Classifier: Environment :: Web Environment
Classifier: Framework :: Django
Classifier: Intended Audience :: Developers
Classifier: License :: OSI Approved :: BSD License
Classifier: Operating System :: OS Independent
Classifier: Programming Language :: Python
Classifier: Programming Language :: Python :: 2
Classifier: Programming Language :: Python :: 2.6
Classifier: Programming Language :: Python :: 2.7
